aiotext/__init__.py
aiotext/aiotext.py
aiotext/lemmatize.py
aiotext/test_aiotext.py
aiotext-1.0.6.dist-info/LICENSE
aiotext-1.0.6.dist-info/METADATA
aiotext-1.0.6.dist-info/WHEEL
aiotext-1.0.6.dist-info/top_level.txt
aiotext-1.0.6.dist-info/RECORD
