Metadata-Version: 2.1
Name: aiotext
Version: 1.0.6
Summary: All in one text processor and cleaner.
Home-page: https://github.com/EricWiener/aiotext
Author: Eric Wiener
Author-email: ericwiener3@gmail.com
License: UNKNOWN
Platform: UNKNOWN
Classifier: Programming Language :: Python :: 3
Classifier: License :: OSI Approved :: MIT License
Classifier: Operating System :: OS Independent
Requires-Dist: scikit-learn
Requires-Dist: pycontractions
Requires-Dist: nltk
